dom
setup.py
dom.egg-info/PKG-INFO
dom.egg-info/SOURCES.txt
dom.egg-info/dependency_links.txt
dom.egg-info/requires.txt
dom.egg-info/top_level.txt
domainr/__init__.py
domainr/core.py